yacpl/__init__.py
yacpl/utils.py
yacpl/yacpl.py
yacpl-1.0.9.dist-info/LICENSE
yacpl-1.0.9.dist-info/METADATA
yacpl-1.0.9.dist-info/WHEEL
yacpl-1.0.9.dist-info/top_level.txt
yacpl-1.0.9.dist-info/RECORD
