Metadata-Version: 2.1
Name: yacpl
Version: 1.0.9
Summary: A simple print()-esque library that supports colors!
Author-email: fily <zeroad69@gmail.com>
Maintainer-email: fily <zeroad69@gmail.com>
License: Mozilla Public License Version 2.0
Project-URL: Homepage, https://github.com/fily-gif/yacpl
Project-URL: Bug Reports, https://github.com/fily-gif/yacpl/issues
Project-URL: Source, https://github.com/fily-gif/yacpl/tree/main
Keywords: yacpl,colorama,yaclp,print,colors,color print,ansi,colours,colour print
Classifier: Development Status :: 5 - Production/Stable
Classifier: Intended Audience :: Developers
Classifier: Topic :: Terminals
Classifier: License :: OSI Approved :: Mozilla Public License 2.0 (MPL 2.0)
Classifier: Programming Language :: Python :: 3.9
Classifier: Programming Language :: Python :: 3.10
Classifier: Programming Language :: Python :: 3.11
Classifier: Programming Language :: Python :: 3.12
Classifier: Programming Language :: Python :: 3.13
Classifier: Programming Language :: Python :: 3 :: Only
Requires-Python: >=3.9
License-File: LICENSE
